x16rv2_hash.cp37-win_amd64.pyd
x16rv2_hash-1.0.dist-info/LICENSE
x16rv2_hash-1.0.dist-info/METADATA
x16rv2_hash-1.0.dist-info/WHEEL
x16rv2_hash-1.0.dist-info/top_level.txt
x16rv2_hash-1.0.dist-info/RECORD
