Metadata-Version: 2.1
Name: x16rv2-hash
Version: 1.0
Summary: Bindings for proof of work used by X16Rv2
Home-page: https://github.com/traysi/x16rv2_hash
Author: Traysi Hylian
Maintainer: Ravencoin community
License: MIT
Keywords: ravencoin,rvn,hashing,x16rv2
Platform: UNKNOWN
